dtlibpc/__init__.py
dtlibpc/dataset.so
dtlibpc/utils.so
dtlibpc-1.0.6.dist-info/METADATA
dtlibpc-1.0.6.dist-info/WHEEL
dtlibpc-1.0.6.dist-info/top_level.txt
dtlibpc-1.0.6.dist-info/RECORD
