Metadata-Version: 2.1
Name: dtlibpc
Version: 1.0.6
Summary: A package to manage datasets.
Author: GTrip
Classifier: Programming Language :: Python :: 3
Classifier: Framework :: Django
Classifier: License :: OSI Approved :: MIT License
Classifier: Operating System :: OS Independent
Requires-Python: >=3.6
Requires-Dist: requests
